{
  "db_name": "PostgreSQL",
  "query": "\n        select host_id, name, url\n        from host\n        where host_group_id = $1\n        order by host_id\n        ",
  "describe": {
    "columns": [
      {
        "ordinal": 0,
        "name": "host_id",
        "type_info": "Int8"
      },
      {
        "ordinal": 1,
        "name": "name",
        "type_info": "Text"
      },
      {
        "ordinal": 2,
        "name": "url",
        "type_info": "Text"
      }
    ],
    "parameters": {
      "Left": [
        "Int8"
      ]
    },
    "nullable": [
      false,
      false,
      false
    ]
  },
  "hash": "34f6812cc26d580bc021e969571586c49e2d7e2fe3598d9176ba3d82e1fa8014"
}
